TSM/TSM.py
TSM/__init__.py
traveling_salesman-1.1.4.dist-info/METADATA
traveling_salesman-1.1.4.dist-info/WHEEL
traveling_salesman-1.1.4.dist-info/top_level.txt
traveling_salesman-1.1.4.dist-info/RECORD
