Metadata-Version: 2.1
Name: traveling-salesman
Version: 1.1.4
Summary: A Python package to plot traveling salesman problem with greedy and smallest increase algorithm.
Home-page: https://github.com/furkankykc/TravelingSalesman.git
Author: Furkan Kıyıkcı
Author-email: furkanfbr@gmail.com
License: MIT
Platform: UNKNOWN
Classifier: Programming Language :: Python :: 3
Classifier: License :: OSI Approved :: MIT License
Classifier: Operating System :: OS Independent
Requires-Python: >=3.6
